README.md
setup.py
redflask/__init__.py
redflask/main.py
redflask.egg-info/PKG-INFO
redflask.egg-info/SOURCES.txt
redflask.egg-info/dependency_links.txt
redflask.egg-info/entry_points.txt
redflask.egg-info/requires.txt
redflask.egg-info/top_level.txt