Metadata-Version: 1.0
Name: redflask
Version: 0.1.5
Summary: Restful framework base on flask without blueprint
Home-page: https://gitee.com/sleepingtree/red_flask
Author: redtree
Author-email: redtree@aliyun.com
License: MIT Licence
Keywords: pip,flask,restful,redflask,cli
Platform: linux
